otai_otobo_znuny/__init__.py
otai_otobo_znuny/models.py
otai_otobo_znuny/oto_znuny_ts_service.py
otai_otobo_znuny/otobo_znuny_plugin.py
otai_otobo_znuny-1.5.14.dist-info/METADATA
otai_otobo_znuny-1.5.14.dist-info/WHEEL
otai_otobo_znuny-1.5.14.dist-info/entry_points.txt
otai_otobo_znuny-1.5.14.dist-info/top_level.txt
otai_otobo_znuny-1.5.14.dist-info/RECORD
